numerizer/__init__.py
numerizer/consts.py
numerizer/numerizer.py
numerizer-0.2.4.dist-info/LICENSE
numerizer-0.2.4.dist-info/METADATA
numerizer-0.2.4.dist-info/WHEEL
numerizer-0.2.4.dist-info/top_level.txt
numerizer-0.2.4.dist-info/RECORD
