Metadata-Version: 2.1
Name: numerizer
Version: 0.2.4
Summary: Python module for converting natural language numbers into ints and floats.
Home-page: https://github.com/jaidevd/numerizer
Download-URL: https://pypi.org/project/numerizer/#files
Maintainer: Jaidev Deshpande
Maintainer-email: deshpande.jaidev@gmail.com
License: MIT
License-File: LICENSE
